payoneer_escrow_sdk/__init__.py
payoneer_escrow_sdk/authenticator.py
payoneer_escrow_sdk/client.py
payoneer_escrow_sdk/api/__init__.py
payoneer_escrow_sdk/api/accounts.py
payoneer_escrow_sdk/api/authentications.py
payoneer_escrow_sdk/api/bank_accounts.py
payoneer_escrow_sdk/api/base_resource.py
payoneer_escrow_sdk/api/disputes.py
payoneer_escrow_sdk/api/documents.py
payoneer_escrow_sdk/api/milestones.py
payoneer_escrow_sdk/api/notes.py
payoneer_escrow_sdk/api/offers.py
payoneer_escrow_sdk/api/order_events.py
payoneer_escrow_sdk/api/order_ledgers.py
payoneer_escrow_sdk/api/orders.py
payoneer_escrow_sdk/api/payment_instructions.py
payoneer_escrow_sdk/api/shipment_carriers.py
payoneer_escrow_sdk/api/shipments.py
payoneer_escrow_sdk/api/users.py
payoneer_escrow_sdk-0.1.0.dist-info/DESCRIPTION.rst
payoneer_escrow_sdk-0.1.0.dist-info/METADATA
payoneer_escrow_sdk-0.1.0.dist-info/RECORD
payoneer_escrow_sdk-0.1.0.dist-info/WHEEL
payoneer_escrow_sdk-0.1.0.dist-info/metadata.json
payoneer_escrow_sdk-0.1.0.dist-info/top_level.txt
