Metadata-Version: 2.0
Name: payoneer-escrow-sdk
Version: 0.1.0
Summary: An SDK for working with the Payoneer Escrow API
Home-page: https://github.com/Payoneer-Escrow/payoneer-escrow-python
Author: Adam J Hartz
Author-email: adamha@payoneer.com
License: MIT
Platform: UNKNOWN
Classifier: Development Status :: 4 - Beta
Classifier: Intended Audience :: Developers
Classifier: License :: OSI Approved :: MIT License
Classifier: Programming Language :: Python :: 2
Classifier: Programming Language :: Python :: 3
Classifier: Topic :: Office/Business :: Financial
Classifier: Topic :: Software Development
Requires-Dist: requests
Provides-Extra: tests
Requires-Dist: nose; extra == 'tests'
